LICENSE
MANIFEST.in
README.md
pyproject.toml
setup.py
src/spleaf/__init__.py
src/spleaf/cov.py
src/spleaf/fenrir.py
src/spleaf/libspleaf.c
src/spleaf/libspleaf.h
src/spleaf/pywrapspleaf.c
src/spleaf/term.py
src/spleaf.egg-info/PKG-INFO
src/spleaf.egg-info/SOURCES.txt
src/spleaf.egg-info/dependency_links.txt
src/spleaf.egg-info/requires.txt
src/spleaf.egg-info/top_level.txt
tests/test_cov.py
tests/test_fenrir.py
tests/test_spleaf.py