Metadata-Version: 2.4
Name: spleaf
Version: 2.1.17
Summary: Symmetric S+LEAF matrix
Author-email: Jean-Baptiste Delisle <jean-baptiste.delisle@unige.ch>
Project-URL: Homepage, https://gitlab.unige.ch/delisle/spleaf
Project-URL: Issues, https://gitlab.unige.ch/delisle/spleaf/-/issues
Classifier: Programming Language :: Python :: 3
Classifier: License :: OSI Approved :: European Union Public Licence 1.2 (EUPL 1.2)
Classifier: Operating System :: OS Independent
Requires-Python: >=3.9
License-File: LICENSE
Requires-Dist: numpy>=1.19
Requires-Dist: scipy>=1.3
Dynamic: license-file
